{
  "generated_at": "2026-04-13T19:05:24.186565+00:00",
  "benchmarks": [
    {
      "scenario": "concurrent_messages",
      "total_requests": 6,
      "concurrency": 2,
      "summary": {
        "requests": 6,
        "success_count": 6,
        "failure_count": 0,
        "success_rate": 100.0,
        "latency": {
          "avg_ms": 58.43,
          "min_ms": 16.66,
          "max_ms": 106.4,
          "p95_ms": 70.61,
          "p99_ms": 70.61
        },
        "errors": {}
      }
    },
    {
      "scenario": "timeout_retry",
      "total_requests": 6,
      "concurrency": 2,
      "forced_timeout_ms": 80.0,
      "retries": 1,
      "summary": {
        "requests": 6,
        "success_count": 6,
        "failure_count": 0,
        "success_rate": 100.0,
        "latency": {
          "avg_ms": 38.03,
          "min_ms": 36.19,
          "max_ms": 39.85,
          "p95_ms": 39.15,
          "p99_ms": 39.15
        },
        "errors": {}
      }
    }
  ]
}